ttf/__init__.py
ttf/cli.py
ttf/server.py
ttf/ttf.py
ttf-0.1.0.dist-info/DESCRIPTION.rst
ttf-0.1.0.dist-info/METADATA
ttf-0.1.0.dist-info/RECORD
ttf-0.1.0.dist-info/WHEEL
ttf-0.1.0.dist-info/entry_points.txt
ttf-0.1.0.dist-info/metadata.json
ttf-0.1.0.dist-info/top_level.txt
