Metadata-Version: 1.1
Name: ttf
Version: 0.1.0
Summary: Ask people for information, through twitter, during a humanitarian response effort.
Home-page: https://github.com/SiggyF/ttf
Author: Fedor Baart
Author-email: fedor.baart@deltares.nl
License: GNU General Public License v3
Keywords: ttf
Platform: UNKNOWN
Classifier: Development Status :: 2 - Pre-Alpha
Classifier: Intended Audience :: Developers
Classifier: License :: OSI Approved :: GNU General Public License v3 (GPLv3)
Classifier: Natural Language :: English
Classifier: Programming Language :: Python :: 2
Classifier: Programming Language :: Python :: 2.6
Classifier: Programming Language :: Python :: 2.7
Classifier: Programming Language :: Python :: 3
Classifier: Programming Language :: Python :: 3.3
Classifier: Programming Language :: Python :: 3.4
Classifier: Programming Language :: Python :: 3.5
